{
  "id": "@SimonB97/win-cli-mcp-server",
  "title": "Windows CLI",
  "description": "MCP server for secure command-line interactions on Windows systems, enabling controlled access to PowerShell, CMD, and Git Bash shells.",
  "tags": [
    "windows"
  ],
  "categories": [
    "Operating Systems",
    "Developer Tools"
  ],
  "creator": "SimonB97",
  "logoUrl": "https://app.mcphub.net/server-configuration/image/windows-cli.svg",
  "publishDate": "2024-12-13T12:00:00Z",
  "rating": 5,
  "sources": {
    "github": "https://github.com/SimonB97/win-cli-mcp-server",
    "npm": "https://www.npmjs.com/package/@simonb97/server-win-cli"
  },
  "type": "stdio",
  "commandInfo": {
    "command": "npx",
    "args": [
      "-y",
      "@simonb97/server-win-cli"
    ]
  }
}